vcontrold/__init__.py
vcontrold/uart.py
vcontrold/vpackets.py
pyvcontrold-0.0.16.dist-info/LICENSE
pyvcontrold-0.0.16.dist-info/METADATA
pyvcontrold-0.0.16.dist-info/WHEEL
pyvcontrold-0.0.16.dist-info/top_level.txt
pyvcontrold-0.0.16.dist-info/RECORD
