Metadata-Version: 2.1
Name: pyvcontrold
Version: 0.0.16
Summary: Library Viessmann heaters
Home-page: https://github.com/bertouttier/pyvcontrold
Download-URL: https://github.com/bertouttier/pyvcontrold
Author: Bert Outtier
Author-email: outtierbert@gmail.com
License: MIT
Platform: UNKNOWN
Classifier: Development Status :: 4 - Beta
Classifier: Intended Audience :: Developers
Classifier: License :: OSI Approved :: MIT License
Classifier: Operating System :: OS Independent
Classifier: Programming Language :: Python :: 3 :: Only
Classifier: Topic :: Home Automation
Classifier: Topic :: Software Development :: Libraries :: Python Modules
License-File: LICENSE
Requires-Dist: async-timeout (>=3.0.1)
Requires-Dist: pyserial-asyncio (>=0.4)
Requires-Dist: scapy (>=2.4.3)
